[
    {
        "id": "1ft9m4w",
        "title": "Will it really be worth it?",
        "url": "https://i.redd.it/mzyepz8h41sd1.png",
        "author": "ChaosOfOrder24",
        "permalink": "https://reddit.com/r/dankmemes/comments/1ft9m4w/will_it_really_be_worth_it/"
    },
    {
        "id": "1hu7l1n",
        "title": "Chill Bro stop spoiling ",
        "url": "https://i.redd.it/ch660d8dl6be1.png",
        "author": "Alarmed-Ad-436",
        "permalink": "https://reddit.com/r/memes/comments/1hu7l1n/chill_bro_stop_spoiling/"
    },
    {
        "id": "1ixt29b",
        "title": "guys... don't",
        "url": "https://i.redd.it/9mwzr1ztv9le1.png",
        "author": "Worth-Muscle-4834",
        "permalink": "https://reddit.com/r/memes/comments/1ixt29b/guys_dont/"
    },
    {
        "id": "1ixmxc6",
        "title": "*Sips tea*",
        "url": "https://i.redd.it/d6r81cnkt7le1.png",
        "author": "Leather-Paramedic-10",
        "permalink": "https://reddit.com/r/memes/comments/1ixmxc6/sips_tea/"
    }
]